mzml2isa/__init__.py
mzml2isa/__main__.py
mzml2isa/_impl.py
mzml2isa/imzml.py
mzml2isa/isa.py
mzml2isa/mzml.py
mzml2isa/parsing.py
mzml2isa/usermeta.py
mzml2isa/utils.py
mzml2isa/ontologies/__init__.py
mzml2isa/ontologies/imagingMS.obo
mzml2isa/ontologies/pato.obo
mzml2isa/ontologies/psi-ms.obo
mzml2isa/ontologies/stato.owl
mzml2isa/templates/__init__.py
mzml2isa/templates/a_imzML.txt
mzml2isa/templates/a_mzML.txt
mzml2isa/templates/i_imzML.txt
mzml2isa/templates/i_mzML.txt
mzml2isa/templates/s_imzML.txt
mzml2isa/templates/s_mzML.txt
mzml2isa-1.1.1.dist-info/COPYING
mzml2isa-1.1.1.dist-info/METADATA
mzml2isa-1.1.1.dist-info/WHEEL
mzml2isa-1.1.1.dist-info/entry_points.txt
mzml2isa-1.1.1.dist-info/top_level.txt
mzml2isa-1.1.1.dist-info/RECORD
