Metadata-Version: 2.1
Name: mzml2isa
Version: 1.1.1
Summary: mzML file parser and converter to ISA-Tab
Home-page: https://github.com/ISA-tools/mzml2isa
Author: Tom Lawson, Martin Larralde
Author-email: tnl495@bham.ac.uk
License: GPLv3
Project-URL: Bug Reports, https://github.com/ISA-tools/mzml2isa/issues
Project-URL: Documentation, http://2isa.readthedocs.io/en/latest/mzml2isa/
Project-URL: Changelog, https://github.com/ISA-tools/mzml2isa/blob/master/CHANGELOG.md
Keywords: metabolomics,mass spectrometry,metabolites,ISA Tab,mzML,parser
Platform: any
Classifier: Intended Audience :: Science/Research
Classifier: Programming Language :: Python :: 3
Classifier: Programming Language :: Python :: 3.6
Classifier: Programming Language :: Python :: 3.7
Classifier: Programming Language :: Python :: 3.8
Classifier: Programming Language :: Python :: 3.9
Classifier: Programming Language :: Python :: 3.10
Classifier: Topic :: Text Processing :: Markup :: XML
Classifier: Topic :: Scientific/Engineering :: Bio-Informatics
Classifier: Topic :: Scientific/Engineering :: Chemistry
Classifier: Topic :: Utilities
Classifier: License :: OSI Approved :: GNU General Public License v3 (GPLv3)
Classifier: Operating System :: OS Independent
Requires-Python: >=3.6
License-File: COPYING
Requires-Dist: fs (~=2.4)
Requires-Dist: pronto (~=2.0)
Requires-Dist: openpyxl (>=2.5)
Requires-Dist: cached-property (~=1.4) ; python_version < "3.8"
Requires-Dist: importlib-resources (>=1.0) ; python_version < "3.9"
Provides-Extra: pb
Requires-Dist: tqdm (~=4.25) ; extra == 'pb'
